[
  { "id": "home-1", "x": 0.25, "y": 0.47, "name": "Pharmacology Book", "desc": "Contains notes about the \"Nightmare suppressant\" and \"Tranquilizer\" that Neml and Nina take" },
  { "id": "home-2", "x": 0.2, "y": 0.37, "name": "Book on Races and the World", "desc": "Tormenian: majority race\nChaotix: race of chaos\nNoctarian: those who bring mutations" },
  { "id": "home-3", "x": 0.38, "y": 0.32, "name": "Outside the Window", "desc": "A large moon is visible" },
  { "id": "home-4", "x": 0.21, "y": 0.75, "name": "Under the Bed", "desc": "There is a self-defense knife Nina hid" },
  { "id": "home-5", "x": 0.63, "y": 0.42, "name": "Empty Bottle", "desc": "An empty bottle that held the Nightmare suppressant\nNeed to buy more" },
  { "id": "home-6", "x": 0.64, "y": 0.6, "name": "Cupboard", "desc": "A baguette is inside" },
  { "id": "home-7", "x": 0.57, "y": 0.48, "name": "Tax Payment Certificate", "desc": "A certificate that Neml and Nina paid taxes in this area" },
  { "id": "stall-1", "x": 0.45, "y": 0.65, "name": "Goods", "desc": "Fruit and other items are lined up" },
  { "id": "stall-2", "x": 0.7, "y": 0.75, "name": "Bolo", "desc": "The shop's mascot dog\nLoves the baguette Nina brings" },
  { "id": "stall-3", "x": 0.7, "y": 0.75, "name": "Bolo", "desc": "...Is that what he looked like?" },
  { "id": "apothecary-1", "x": 0.55, "y": 0.58, "name": "Pharmacology Book", "desc": "The page for \"Tranquilizer\" is open\nApparently compounded from Kasra fruit" },
  { "id": "apothecary-2", "x": 0.22, "y": 0.42, "name": "Tranquilizer", "desc": "Seems to be sold out" },
  { "id": "apothecary-3", "x": 0.165, "y": 0.425, "name": "Colorful Medicine", "desc": "Suspiciously colored medicine" },
  { "id": "apothecary-4", "x": 0.1, "y": 0.43, "name": "Nightmare Suppressant", "desc": "The medicine Neml and Nina take" },
  { "id": "apothecary-5", "x": 0.78, "y": 0.4, "name": "Exam Room", "desc": "Never been inside" },
  { "id": "shore-1", "x": 0.68, "y": 0.7, "name": "Ceryth's Belongings", "desc": "A magic compass\nPointing beyond the sea" },
  { "id": "shore-2", "x": 0.62, "y": 0.66, "name": "Ceryth's Belongings", "desc": "A bottle of Tranquilizer\nIt's empty" },
  { "id": "shore-3", "x": 0.255, "y": 0.16, "name": "Moon", "desc": "It seems to look bigger than before" },
  { "id": "wulfric-home-1", "x": 0.42, "y": 0.25, "name": "Cutlass", "desc": "A very large cutlass" },
  { "id": "wulfric-home-2", "x": 0.5, "y": 0.35, "name": "Old Map", "desc": "A map from before the great flood\nThe terrain of the Chaotix region is very different from now" },
  { "id": "wulfric-home-3", "x": 0.16, "y": 0.4, "name": "Shelf", "desc": "Food and liquor are there" }
]
